{
  "authors": [
    "Gan Luo",
    "Lingmin Chen",
    "Yi Li",
    "Yu Fan",
    "Duyang Wang",
    "Yufan Yang",
    "Lu Gao",
    "Ruotian Jiang",
    "Zhenlei Song"
  ],
  "authors_citations": [
    "Key Laboratory of Drug-Targeting and Drug Delivery System of the Education Ministry and Sichuan Province, Sichuan Engineering Laboratory for Plant-Sourced Drug and Sichuan Research Center for Drug Precision Industrial Technology, West China School of Pharmacy, Sichuan University, Chengdu, 610041, China",
    "Laboratory of Anesthesia and Critical Care Medicine, Department of Anesthesiology, National-Local Joint Engineering Research Center of Translational Medicine of Anesthesiology, West China Hospital of Sichuan University, Chengdu, Sichuan, 610000, China"
  ],
  "title": "Asymmetric total synthesis and antidepressant activity of (−)-sila-mesembranol bearing a silicon stereocenter",
  "title_citations": [
    "page 1, title section"
  ],
  "publication_year": 2021,
  "publication_year_citations": [
    "page 1, header section"
  ],
  "doi": "10.1039/d1qo00682g",
  "doi_citations": [
    "page 1, left sidebar"
  ],
  "venue": "Organic Chemistry Frontiers",
  "venue_citations": [
    "page 1, header section"
  ]
}